LICENSE
README.md
pyproject.toml
setup.cfg
setup.py
src/XGenTS/__init__.py
src/XGenTS/config.py
src/XGenTS/customexception.py
src/XGenTS/data/__init__.py
src/XGenTS/data/datasets.py
src/XGenTS/data/preprocessors.py
src/XGenTS/models/__init__.py
src/XGenTS/models/adversarial_ae/__init__.py
src/XGenTS/models/adversarial_ae/adversarial_ae_config.py
src/XGenTS/models/adversarial_ae/adversarial_ae_model.py
src/XGenTS/models/ae/__init__.py
src/XGenTS/models/ae/ae_config.py
src/XGenTS/models/ae/ae_model.py
src/XGenTS/models/auto_model/__init__.py
src/XGenTS/models/auto_model/auto_config.py
src/XGenTS/models/auto_model/auto_model.py
src/XGenTS/models/base/__init__.py
src/XGenTS/models/base/base_config.py
src/XGenTS/models/base/base_model.py
src/XGenTS/models/base/base_utils.py
src/XGenTS/models/beta_tc_vae/__init__.py
src/XGenTS/models/beta_tc_vae/beta_tc_vae_config.py
src/XGenTS/models/beta_tc_vae/beta_tc_vae_model.py
src/XGenTS/models/beta_vae/__init__.py
src/XGenTS/models/beta_vae/beta_vae_config.py
src/XGenTS/models/beta_vae/beta_vae_model.py
src/XGenTS/models/ciwae/__init__.py
src/XGenTS/models/ciwae/ciwae_config.py
src/XGenTS/models/ciwae/ciwae_model.py
src/XGenTS/models/disentangled_beta_vae/__init__.py
src/XGenTS/models/disentangled_beta_vae/disentangled_beta_vae_config.py
src/XGenTS/models/disentangled_beta_vae/disentangled_beta_vae_model.py
src/XGenTS/models/factor_vae/__init__.py
src/XGenTS/models/factor_vae/factor_vae_config.py
src/XGenTS/models/factor_vae/factor_vae_model.py
src/XGenTS/models/factor_vae/factor_vae_utils.py
src/XGenTS/models/hvae/__init__.py
src/XGenTS/models/hvae/hvae_config.py
src/XGenTS/models/hvae/hvae_model.py
src/XGenTS/models/info_vae/__init__.py
src/XGenTS/models/info_vae/info_vae_config.py
src/XGenTS/models/info_vae/info_vae_model.py
src/XGenTS/models/iwae/__init__.py
src/XGenTS/models/iwae/iwae_config.py
src/XGenTS/models/iwae/iwae_model.py
src/XGenTS/models/miwae/__init__.py
src/XGenTS/models/miwae/miwae_config.py
src/XGen_Time_Series.egg-info/PKG-INFO
src/XGen_Time_Series.egg-info/SOURCES.txt
src/XGen_Time_Series.egg-info/dependency_links.txt
src/XGen_Time_Series.egg-info/requires.txt
src/XGen_Time_Series.egg-info/top_level.txt