Metadata-Version: 2.1
Name: XGen-Time-Series
Version: 0.1.1
Summary: An eXplainable framework for Generative Time Series in Python
Home-page: https://github.com/XgenTimeSeries/xgen-timeseries
Author: Khalid OUBLAL (S2A team Institut Polytechnique de Paris)
Author-email: khalid.oublal@polytechnique.edu
Project-URL: Bug Tracker, https://github.com/XgenTimeSeries/xgen-timeseries/issues
Classifier: Programming Language :: Python :: 3
Classifier: Programming Language :: Python :: 3.7
Classifier: Programming Language :: Python :: 3.8
Classifier: Programming Language :: Python :: 3.9
Classifier: License :: OSI Approved :: Apache Software License
Classifier: Operating System :: OS Independent
Requires-Python: >=3.7
License-File: LICENSE
